MANIFEST.in
README.rst
setup.py
docs/conf.py
docs/index.rst
xbob/__init__.py
xbob.db.lfw.egg-info/PKG-INFO
xbob.db.lfw.egg-info/SOURCES.txt
xbob.db.lfw.egg-info/dependency_links.txt
xbob.db.lfw.egg-info/entry_points.txt
xbob.db.lfw.egg-info/namespace_packages.txt
xbob.db.lfw.egg-info/not-zip-safe
xbob.db.lfw.egg-info/requires.txt
xbob.db.lfw.egg-info/top_level.txt
xbob/db/__init__.py
xbob/db/lfw/__init__.py
xbob/db/lfw/create.py
xbob/db/lfw/db.sql3
xbob/db/lfw/driver.py
xbob/db/lfw/models.py
xbob/db/lfw/query.py
xbob/db/lfw/test.py